<?xml version="1.0" encoding="UTF-8"?>
<site>
   <description name="Project Euler Eclipse Plugin Update Site" url="http://code.lucaswerkmeister.de/peep">
      This update site contains the Project Euler Eclipse plugins.
   </description>
   <feature url="features/de.lucaswerkmeister.peep.core.feature_1.0.2.1.jar" id="de.lucaswerkmeister.peep.core.feature" version="1.0.2.1">
      <category name="de.lucaswerkmeister.peep"/>
   </feature>
   <feature url="features/de.lucaswerkmeister.peep.git.feature_1.0.0.3.jar" id="de.lucaswerkmeister.peep.git.feature" version="1.0.0.3">
      <category name="de.lucaswerkmeister.peep"/>
   </feature>
   <category-def name="de.lucaswerkmeister.peep" label="Project Euler Eclipse Plugin">
      <description>
         Contains several plugins to simplify the workflow when working on Project Euler with Eclipse + Java.
      </description>
   </category-def>
</site>
